setup.py
bootup/__init__.py
bootup/bootup.py
bootup/fixtures.py
bootup/models.py
bootup/profiles.py
bootup/sites.py
bootup/tests.py
bootup/users.py
bootup/util.py
django_bootup.egg-info/PKG-INFO
django_bootup.egg-info/SOURCES.txt
django_bootup.egg-info/dependency_links.txt
django_bootup.egg-info/top_level.txt