Metadata-Version: 1.1
Name: django-bootup
Version: 1.0.1
Summary: A Django bootup application that helps with quick and secure bootup of your django project.
Home-page: https://github.com/un33k/django-bootup
Author: Val Neekman
Author-email: info@neekware.com
License: BSD
Platform: UNKNOWN
Classifier: Development Status :: 4 - Beta
Classifier: Environment :: Web Environment
Classifier: Intended Audience :: Developers
Classifier: License :: OSI Approved :: BSD License
Classifier: Operating System :: OS Independent
Classifier: Programming Language :: Python
Classifier: Topic :: Utilities
